Balu_test_packaage/__init__.py
Balu_test_packaage/airthmetic.py
Balu_test_packaage/sub_pkg/__init__.py
Balu_test_packaage/sub_pkg/check.py
Balu_test_Pacakage-0.0.2.dist-info/METADATA
Balu_test_Pacakage-0.0.2.dist-info/WHEEL
Balu_test_Pacakage-0.0.2.dist-info/top_level.txt
Balu_test_Pacakage-0.0.2.dist-info/RECORD
